{
  "id": "148249584f7b9c7cd6e23d7de6fc42dea411e426",
  "title": "Chinese Pandas Leave Japanese Zoo",
  "summary_full": "As Japan and China feud, an animal long used in Chinese diplomacy has been summoned back home.",
  "summary_public": "As Japan and China feud, an animal long used in Chinese diplomacy has been summoned back home.",
  "url": "https://www.nytimes.com/2026/01/26/world/asia/japan-pandas-china.html",
  "published_at": "2026-01-26T21:59:41+00:00",
  "source": "NYT > World News",
  "language": "en",
  "countries_detected": [],
  "countries_scored": [],
  "sentiment": {},
  "processed_at": null
}