{
  "id": "2ee8c6b66cf7ce1375d0199663665782827c085d",
  "title": "Panama Court Strikes Down Hong Kong Firm’s Canal Contract",
  "summary_full": "President Trump has said he wants American control of the canal, putting the longtime ports operator, CK Hutchison, in the cross-hairs of the U.S.-China trade conflict.",
  "summary_public": "President Trump has said he wants American control of the canal, putting the longtime ports operator, CK Hutchison, in the cross-hairs of the U.S.-China trade conflict.",
  "url": "https://www.nytimes.com/2026/01/30/business/panama-canal-ck-hutchison.html",
  "published_at": "2026-01-30T05:11:44+00:00",
  "source": "NYT > World News",
  "language": "en",
  "countries_detected": [],
  "countries_scored": []
}