{
  "id": "34fb034c388257f05e3b703eabb245dad395bdc7",
  "title": "US government partially shuts down despite last minute funding deal",
  "summary_full": "The soonest the US House of Representatives can vote on the funding deal and end the shutdown is Monday.",
  "summary_public": "The soonest the US House of Representatives can vote on the funding deal and end the shutdown is Monday.",
  "url": "https://www.bbc.com/news/articles/ce8rk33dpvmo?at_medium=RSS&at_campaign=rss",
  "published_at": "2026-01-31T05:10:27+00:00",
  "source": "BBC News - World",
  "language": "en",
  "countries_detected": [],
  "countries_scored": []
}