{
  "id": "45d0675dc7f3ec5d533ef0642dce582c9bc46964",
  "title": "Doomsday Clock Ticks Closer Than Ever to Apocalypse",
  "summary_full": "Wars, climate change, disruptive technologies and the rise of autocracy over the past year prompted scientists to set the clock at 85 seconds to midnight.",
  "summary_public": "Wars, climate change, disruptive technologies and the rise of autocracy over the past year prompted scientists to set the clock at 85 seconds to midnight.",
  "url": "https://www.nytimes.com/2026/01/28/us/doomsday-clock-2026.html",
  "published_at": "2026-01-28T11:57:41+00:00",
  "source": "NYT > World News",
  "language": "en",
  "countries_detected": [],
  "countries_scored": []
}