{
  "id": "4df9214e051527b6c13ef88a047ff455f38971f6",
  "title": "ICE Begins Buying 'Mega' Warehouse Detention Centres Across US",
  "summary_full": "At least three people have died at the camp over the past two months.",
  "summary_public": "At least three people have died at the camp over the past two months.",
  "url": "https://www.ndtv.com/world-news/ice-spends-millions-on-mega-warehouse-detention-centers-across-us-10911622#publisher=newsstand",
  "published_at": "2026-01-30T05:29:28+00:00",
  "source": "NDTV News - World-news",
  "language": "en",
  "countries_detected": [],
  "countries_scored": [],
  "sentiment": {},
  "processed_at": null
}