{
  "id": "6cf8c634fe81f966026b144d8a12ed3cd3e9b2f2",
  "title": "‘It’s like a gift from God’: undocumented foreign workers welcome Spanish amnesty",
  "summary_full": "Half a million migrants will be ‘regularised’ under plans to boost economic growth that have angered rightwing partiesNot everyone has been enthused by the Spanish government’s decision this week to buck European political trends by announcing plans to regularise 500,000 undocumented migrants and asylum seekers to boost “economic growth and social cohesion”.Alberto Núñez Feijóo, the leader of the conservative People’s party (PP), described the move as a reward for “illegality” that would bring more people into the country and “overwhelm our public services”. Continue reading...",
  "summary_public": "Half a million migrants will be ‘regularised’ under plans to boost economic growth that have angered rightwing partiesNot everyone has been enthused by the Spanish government’s decision this week to buck European politic…",
  "url": "https://www.theguardian.com/world/2026/jan/31/undocumented-foreign-workers-welcome-spanish-amnesty",
  "published_at": "2026-01-31T05:00:49+00:00",
  "source": "World news - The Guardian",
  "language": "en",
  "countries_detected": [
    "ES"
  ],
  "countries_scored": [
    "ES"
  ]
}