{
  "id": "9648703e292c53ff14c6ad0fc095dd26f8847e09",
  "title": "Trump targets Canadian aircraft in latest tariff threat, says he'll 'decertify' Bombardier jets | CBC News",
  "summary_full": "&#32; submitted by &#32;  /u/Ecstatic-Ganache921   [link] &#32; [comments]",
  "summary_public": "&#32; submitted by &#32;  /u/Ecstatic-Ganache921   [link] &#32; [comments]",
  "url": "https://www.reddit.com/r/worldnews/comments/1qqqbvj/trump_targets_canadian_aircraft_in_latest_tariff/",
  "published_at": "2026-01-30T00:34:22+00:00",
  "source": "World News (Reddit)",
  "language": "en",
  "countries_detected": [],
  "countries_scored": [],
  "sentiment": {},
  "processed_at": null
}