{
  "id": "a8d0bf8208dcd018ea17742a555cb5612b8e2289",
  "title": "UK’s first rapid-charging battery train ready for boarding this weekend",
  "summary_full": "Great Western Railway service recharges in three and a half minutes between trips on west London lineThe UK’s first superfast-charging train running only on battery power will come into passenger service this weekend – operating a five-mile return route in west London.Great Western Railway (GWR) will send the converted London Underground train out from 5.30am to cover the full Saturday timetable on the West Ealing to Greenford branch line, four stops and 12 minutes each way, and now carrying up to 273 passengers, should its celebrity stoke up the demand. Continue reading...",
  "summary_public": "Great Western Railway service recharges in three and a half minutes between trips on west London lineThe UK’s first superfast-charging train running only on battery power will come into passenger service this weekend – o…",
  "url": "https://www.theguardian.com/business/2026/jan/30/uk-first-rapid-charging-battery-train",
  "published_at": "2026-01-30T05:00:13+00:00",
  "source": "World news - The Guardian",
  "language": "en",
  "countries_detected": [
    "GB"
  ],
  "countries_scored": [
    "GB"
  ]
}