{
  "id": "c9739851ae6e4f56ae0febf2a680c9f68106515d",
  "title": "Spain’s rail crash probe challenges socialist government’s safety assurances",
  "summary_full": "Infrastructure safety questions mount as experts dispute claims defects would have gone undetected",
  "summary_public": "Infrastructure safety questions mount as experts dispute claims defects would have gone undetected",
  "url": "https://www.euractiv.com/news/spains-rail-crash-probe-challenges-socialist-government-safety-assurance/",
  "published_at": "2026-01-30T05:00:38+00:00",
  "source": "Euractiv",
  "language": "en",
  "countries_detected": [
    "ES"
  ],
  "countries_scored": [
    "ES"
  ],
  "sentiment": {
    "compound": 0.0516,
    "positive": 0.287,
    "neutral": 0.463,
    "negative": 0.25
  },
  "processed_at": "2026-01-30T06:34:32+00:00"
}