{
  "id": "e47613a66e301cd27d5201a9877adf8ccf13b200",
  "title": "Luigi Mangione won't face death penalty in CEO murder case, federal judge rules",
  "summary_full": "Luigi Mangione is accusing of fatally shooting UnitedHealthcare CEO Brian Thompson on a New York City street in December 2024.",
  "summary_public": "Luigi Mangione is accusing of fatally shooting UnitedHealthcare CEO Brian Thompson on a New York City street in December 2024.",
  "url": "https://www.cnbc.com/2026/01/30/luigi-mangione-death-penalty-unitedhealth-thompson-doj.html",
  "published_at": "2026-01-30T21:23:38+00:00",
  "source": "International: Top News And Analysis",
  "language": "en",
  "countries_detected": [],
  "countries_scored": [],
  "sentiment": {},
  "processed_at": null
}