{
  "id": "0d23dca502f38056a4351a0f59571995de0ce2d3",
  "title": "Australian woman dies after becoming snagged in ski lift in Japan",
  "summary_full": "The 22-year-old became caught in a chairlift and was suspended in midair before having a heart attack, officials say.",
  "summary_public": "The 22-year-old became caught in a chairlift and was suspended in midair before having a heart attack, officials say.",
  "url": "https://www.bbc.com/news/articles/cvgdyj5n3m6o?at_medium=RSS&at_campaign=rss",
  "published_at": "2026-02-02T12:43:00+00:00",
  "source": "BBC News - World",
  "language": "en",
  "countries_detected": [],
  "countries_scored": []
}