{
  "id": "3c364e559bcae78adf93b23884a12e513a5dac6f",
  "title": "Amid Claims Around Sentient AI, Sundar Pichai's Comment On Models \"Unexpected Capabilities\" Viral Again",
  "summary_full": "Sundar Pichai said that AI is changing the way people interact with technology.",
  "summary_public": "Sundar Pichai said that AI is changing the way people interact with technology.",
  "url": "https://www.ndtv.com/world-news/google-translated-bengali-on-its-own-google-ceo-sundar-pichais-old-video-on-nature-of-ai-goes-viral-10929712#publisher=newsstand",
  "published_at": "2026-02-02T07:57:49+00:00",
  "source": "NDTV News - World-news",
  "language": "en",
  "countries_detected": [],
  "countries_scored": []
}