{
  "country": "AL",
  "score": 100,
  "score_label": "No Commentary",
  "assessment": "Mostly neutral/positive coverage",
  "trend": null,
  "sources": 2,
  "sentiment": {
    "positive": 0,
    "neutral": 2,
    "negative": 0
  },
  "latest_articles": [
    {
      "id": "3886e8c1b5956b36f63be9946bff49e3c7521a88",
      "title": "Albania lifts TikTok ban",
      "summary": "The country blocked access to the platform last March after a classmate fatally stabbed a teenager following a fight sparked by a social media dispute",
      "url": "https://www.euractiv.com/news/albania-lifts-tiktok-ban/",
      "source": "Euractiv",
      "published_at": "2026-02-05T10:25:10+00:00",
      "sentiment": "neutral",
      "confidence": 0.3,
      "evidence": "Albania lifts TikTok ban"
    },
    {
      "id": "67b156e53edb7dea2593c36e684e6ae7ccfa7a6a",
      "title": "Albania Created an ‘A.I. Minister’ to Curb Corruption. Then Its Developers Were Accused of Graft.",
      "summary": "The Albanian avatar known as Diella, a public anticorruption crusader, has been described as the world’s first government minister created by artificial intelligence.",
      "url": "https://www.nytimes.com/2026/01/27/world/europe/albania-ai-corruption-graft.html",
      "source": "NYT > World News",
      "published_at": "2026-01-27T15:57:00+00:00",
      "sentiment": "neutral",
      "confidence": 0.3,
      "evidence": "Albania Created an ‘A.I. Minister’ to Curb Corruption"
    }
  ],
  "window_days": 90,
  "last_updated": "2026-02-14T09:45:43Z"
}