{
  "country": "DZ",
  "score": 100,
  "score_label": "No Commentary",
  "assessment": "Mostly neutral/positive coverage",
  "trend": null,
  "sources": 1,
  "sentiment": {
    "positive": 0,
    "neutral": 1,
    "negative": 0
  },
  "latest_articles": [
    {
      "id": "31e18f5f751f8bcc91ac1a11ae1ca9baa2559289",
      "title": "Russia claims its Africa Corps group prevented coup in Mali after rebels seize towns",
      "summary": "Kremlin-controlled paramilitaries also alleged it inflicted ‘irreplaceable losses’ on insurgents avoiding civilian casualtiesRussia’s defence ministry has claimed its Africa Corps – the successor to the former Wagner mer…",
      "url": "https://www.theguardian.com/world/2026/apr/28/russia-claims-its-africa-corps-group-prevented-coup-in-mali-after-rebels-seize-towns",
      "source": "World news - The Guardian",
      "published_at": "2026-04-28T17:07:27+00:00",
      "sentiment": "neutral",
      "confidence": 0.1,
      "evidence": "near the Algerian border"
    }
  ],
  "window_days": 90,
  "last_updated": "2026-07-14T11:02:18Z"
}