{
  "last_updated": "2026-01-31T09:08:59Z",
  "window_days": 90,
  "countries": {
    "GL": {
      "score": 90,
      "trend": 0,
      "sources": 17,
      "last_updated": "2026-01-31T09:08:59Z"
    },
    "IS": {
      "score": 90,
      "trend": null,
      "sources": 0,
      "last_updated": "2026-01-31T09:08:59Z"
    },
    "MA": {
      "score": 90,
      "trend": null,
      "sources": 0,
      "last_updated": "2026-01-31T09:08:59Z"
    },
    "TN": {
      "score": 90,
      "trend": null,
      "sources": 0,
      "last_updated": "2026-01-31T09:08:59Z"
    },
    "DZ": {
      "score": 90,
      "trend": null,
      "sources": 0,
      "last_updated": "2026-01-31T09:08:59Z"
    },
    "BY": {
      "score": 90,
      "trend": 0,
      "sources": 3,
      "last_updated": "2026-01-31T09:08:59Z"
    },
    "JO": {
      "score": 90,
      "trend": null,
      "sources": 0,
      "last_updated": "2026-01-31T09:08:59Z"
    },
    "KZ": {
      "score": 90,
      "trend": null,
      "sources": 0,
      "last_updated": "2026-01-31T09:08:59Z"
    },
    "NO": {
      "score": 90,
      "trend": 0,
      "sources": 3,
      "last_updated": "2026-01-31T09:08:59Z"
    },
    "UA": {
      "score": 89,
      "trend": 0,
      "sources": 46,
      "last_updated": "2026-01-31T09:08:59Z"
    },
    "IL": {
      "score": 90,
      "trend": 3,
      "sources": 19,
      "last_updated": "2026-01-31T09:08:59Z"
    },
    "SA": {
      "score": 90,
      "trend": 0,
      "sources": 7,
      "last_updated": "2026-01-31T09:08:59Z"
    },
    "IQ": {
      "score": 90,
      "trend": 0,
      "sources": 2,
      "last_updated": "2026-01-31T09:08:59Z"
    },
    "AZ": {
      "score": 90,
      "trend": null,
      "sources": 0,
      "last_updated": "2026-01-31T09:08:59Z"
    },
    "IR": {
      "score": 90,
      "trend": 3,
      "sources": 64,
      "last_updated": "2026-01-31T09:08:59Z"
    },
    "GE": {
      "score": 90,
      "trend": 0,
      "sources": 1,
      "last_updated": "2026-01-31T09:08:59Z"
    },
    "SY": {
      "score": 90,
      "trend": 0,
      "sources": 6,
      "last_updated": "2026-01-31T09:08:59Z"
    },
    "TR": {
      "score": 90,
      "trend": 0,
      "sources": 3,
      "last_updated": "2026-01-31T09:08:59Z"
    },
    "AM": {
      "score": 90,
      "trend": null,
      "sources": 0,
      "last_updated": "2026-01-31T09:08:59Z"
    },
    "CY": {
      "score": 90,
      "trend": 0,
      "sources": 55,
      "last_updated": "2026-01-31T09:08:59Z"
    },
    "CH": {
      "score": 90,
      "trend": 0,
      "sources": 3,
      "last_updated": "2026-01-31T09:08:59Z"
    },
    "MD": {
      "score": 90,
      "trend": null,
      "sources": 0,
      "last_updated": "2026-01-31T09:08:59Z"
    },
    "AL": {
      "score": 90,
      "trend": 0,
      "sources": 1,
      "last_updated": "2026-01-31T09:08:59Z"
    },
    "LB": {
      "score": 90,
      "trend": null,
      "sources": 0,
      "last_updated": "2026-01-31T09:08:59Z"
    },
    "AD": {
      "score": 90,
      "trend": null,
      "sources": 0,
      "last_updated": "2026-01-31T09:08:59Z"
    },
    "MC": {
      "score": 90,
      "trend": null,
      "sources": 0,
      "last_updated": "2026-01-31T09:08:59Z"
    },
    "LI": {
      "score": 90,
      "trend": null,
      "sources": 0,
      "last_updated": "2026-01-31T09:08:59Z"
    },
    "BA": {
      "score": 90,
      "trend": 0,
      "sources": 1,
      "last_updated": "2026-01-31T09:08:59Z"
    },
    "MK": {
      "score": 90,
      "trend": 0,
      "sources": 1,
      "last_updated": "2026-01-31T09:08:59Z"
    },
    "HR": {
      "score": 90,
      "trend": 0,
      "sources": 55,
      "last_updated": "2026-01-31T09:08:59Z"
    },
    "PT": {
      "score": 90,
      "trend": 0,
      "sources": 56,
      "last_updated": "2026-01-31T09:08:59Z"
    },
    "ES": {
      "score": 90,
      "trend": 0,
      "sources": 62,
      "last_updated": "2026-01-31T09:08:59Z"
    },
    "BE": {
      "score": 90,
      "trend": 0,
      "sources": 69,
      "last_updated": "2026-01-31T09:08:59Z"
    },
    "IT": {
      "score": 90,
      "trend": 0,
      "sources": 65,
      "last_updated": "2026-01-31T09:08:59Z"
    },
    "PL": {
      "score": 90,
      "trend": 0,
      "sources": 60,
      "last_updated": "2026-01-31T09:08:59Z"
    },
    "GR": {
      "score": 90,
      "trend": 0,
      "sources": 56,
      "last_updated": "2026-01-31T09:08:59Z"
    },
    "FI": {
      "score": 90,
      "trend": 0,
      "sources": 55,
      "last_updated": "2026-01-31T09:08:59Z"
    },
    "DE": {
      "score": 90,
      "trend": 0,
      "sources": 67,
      "last_updated": "2026-01-31T09:08:59Z"
    },
    "SE": {
      "score": 90,
      "trend": 0,
      "sources": 57,
      "last_updated": "2026-01-31T09:08:59Z"
    },
    "IE": {
      "score": 90,
      "trend": 0,
      "sources": 55,
      "last_updated": "2026-01-31T09:08:59Z"
    },
    "GB": {
      "score": 89,
      "trend": 1,
      "sources": 74,
      "last_updated": "2026-01-31T09:08:59Z"
    },
    "AT": {
      "score": 90,
      "trend": 0,
      "sources": 54,
      "last_updated": "2026-01-31T09:08:59Z"
    },
    "CZ": {
      "score": 90,
      "trend": 0,
      "sources": 54,
      "last_updated": "2026-01-31T09:08:59Z"
    },
    "SK": {
      "score": 90,
      "trend": 0,
      "sources": 55,
      "last_updated": "2026-01-31T09:08:59Z"
    },
    "HU": {
      "score": 90,
      "trend": 0,
      "sources": 59,
      "last_updated": "2026-01-31T09:08:59Z"
    },
    "LT": {
      "score": 90,
      "trend": 0,
      "sources": 56,
      "last_updated": "2026-01-31T09:08:59Z"
    },
    "LV": {
      "score": 90,
      "trend": 0,
      "sources": 105,
      "last_updated": "2026-01-31T09:08:59Z"
    },
    "RO": {
      "score": 90,
      "trend": 0,
      "sources": 55,
      "last_updated": "2026-01-31T09:08:59Z"
    },
    "BG": {
      "score": 90,
      "trend": 0,
      "sources": 54,
      "last_updated": "2026-01-31T09:08:59Z"
    },
    "EE": {
      "score": 90,
      "trend": 0,
      "sources": 60,
      "last_updated": "2026-01-31T09:08:59Z"
    },
    "SM": {
      "score": 90,
      "trend": null,
      "sources": 0,
      "last_updated": "2026-01-31T09:08:59Z"
    },
    "LU": {
      "score": 90,
      "trend": 0,
      "sources": 55,
      "last_updated": "2026-01-31T09:08:59Z"
    },
    "FR": {
      "score": 90,
      "trend": 0,
      "sources": 77,
      "last_updated": "2026-01-31T09:08:59Z"
    },
    "NL": {
      "score": 90,
      "trend": 0,
      "sources": 63,
      "last_updated": "2026-01-31T09:08:59Z"
    },
    "SI": {
      "score": 90,
      "trend": 0,
      "sources": 54,
      "last_updated": "2026-01-31T09:08:59Z"
    },
    "DK": {
      "score": 90,
      "trend": 0,
      "sources": 67,
      "last_updated": "2026-01-31T09:08:59Z"
    },
    "RU": {
      "score": 90,
      "trend": 0,
      "sources": 43,
      "last_updated": "2026-01-31T09:08:59Z"
    },
    "MT": {
      "score": 90,
      "trend": 0,
      "sources": 54,
      "last_updated": "2026-01-31T09:08:59Z"
    },
    "ME": {
      "score": 90,
      "trend": 0,
      "sources": 2,
      "last_updated": "2026-01-31T09:08:59Z"
    },
    "RS": {
      "score": 90,
      "trend": null,
      "sources": 0,
      "last_updated": "2026-01-31T09:08:59Z"
    }
  }
}